odoo/addons/account_invoice_start_end_dates_move/README.rst
odoo/addons/account_invoice_start_end_dates_move/__init__.py
odoo/addons/account_invoice_start_end_dates_move/__manifest__.py
odoo/addons/account_invoice_start_end_dates_move/i18n/account_invoice_start_end_dates_move.pot
odoo/addons/account_invoice_start_end_dates_move/i18n/es.po
odoo/addons/account_invoice_start_end_dates_move/i18n/it.po
odoo/addons/account_invoice_start_end_dates_move/models/__init__.py
odoo/addons/account_invoice_start_end_dates_move/models/account_move.py
odoo/addons/account_invoice_start_end_dates_move/models/res_company.py
odoo/addons/account_invoice_start_end_dates_move/models/res_config_settings.py
odoo/addons/account_invoice_start_end_dates_move/readme/CONFIGURE.rst
odoo/addons/account_invoice_start_end_dates_move/readme/CONTRIBUTORS.rst
odoo/addons/account_invoice_start_end_dates_move/readme/DESCRIPTION.rst
odoo/addons/account_invoice_start_end_dates_move/readme/USAGE.rst
odoo/addons/account_invoice_start_end_dates_move/static/description/icon.png
odoo/addons/account_invoice_start_end_dates_move/static/description/index.html
odoo/addons/account_invoice_start_end_dates_move/tests/__init__.py
odoo/addons/account_invoice_start_end_dates_move/tests/test_account_invoice_start_end_dates_move.py
odoo/addons/account_invoice_start_end_dates_move/views/account_move.xml
odoo/addons/account_invoice_start_end_dates_move/views/res_config_settings.xml
odoo14_addon_account_invoice_start_end_dates_move-14.0.1.0.1.dev6.dist-info/METADATA
odoo14_addon_account_invoice_start_end_dates_move-14.0.1.0.1.dev6.dist-info/WHEEL
odoo14_addon_account_invoice_start_end_dates_move-14.0.1.0.1.dev6.dist-info/top_level.txt
odoo14_addon_account_invoice_start_end_dates_move-14.0.1.0.1.dev6.dist-info/RECORD
